Workbook

Sheet Parámetros
A1: Parámetro | B1: Valor | C1: Fuente | D1: Fecha de consulta
A2: RMV | B2: 1230 | C2: D.S. de la RMV, vigente desde el 1 de octubre de 2026 | D2: 26/10/2026
A3: % asignación familiar | B3: 0.1 | C3: Ley 25129 | D3: 26/10/2026
A4: Asignación familiar | B4: =B2*B3 -> 123 | C4: Calculado: 10% de la RMV | D4: 26/10/2026
A5: ONP | B5: 0.13 | C5: D.L. 19990 | D5: 26/10/2026
A6: EsSalud | B6: 0.09 | C6: Ley 26790 | D6: 26/10/2026
A7: Recargo horas extras 25% | B7: 1.25 | C7: Normas de jornada y sobretiempo | D7: 26/10/2026
A8: Recargo horas extras 35% | B8: 1.35 | C8: Normas de jornada y sobretiempo | D8: 26/10/2026
A9: Días del mes | B9: 30 | C9: Convención del trabajo | D9: 26/10/2026
A10: Horas por día | B10: 8 | C10: Convención del trabajo | D10: 26/10/2026
A12: Tasas AFP | C12: Se usa la comisión sobre remuneración (flujo), que es la que pide el lab. Valores de la SBS, mes de devengue 2026-10
A13: AFP | B13: Fondo | C13: Comisión | D13: Seguro | E13: Fuente | F13: Fecha de consulta
A14: AFP Ejemplo | B14: 0.1 | C14: 0.016 | D14: 0.0135 | E14: Valores de prueba para los casos 1 a 4 | F14: 46321
A15: Habitat | B15: 0.1 | C15: 0.0147 | D15: 0.0137 | E15: SBS, Comisiones y Primas de Seguro del SPP, mes de devengue 2026-10 (www.sbs.gob.pe) | F15: 46321
A16: Integra | B16: 0.1 | C16: 0.0155 | D16: 0.0137 | E16: SBS, Comisiones y Primas de Seguro del SPP, mes de devengue 2026-10 (www.sbs.gob.pe) | F16: 46321
A17: Prima | B17: 0.1 | C17: 0.016 | D17: 0.0137 | E17: SBS, Comisiones y Primas de Seguro del SPP, mes de devengue 2026-10 (www.sbs.gob.pe) | F17: 46321
A18: Profuturo | B18: 0.1 | C18: 0.0169 | D18: 0.0137 | E18: SBS, Comisiones y Primas de Seguro del SPP, mes de devengue 2026-10 (www.sbs.gob.pe) | F18: 46321

Sheet Boleta
A1: BOLETA DE EJEMPLO
A3: DATOS DE ENTRADA (celdas amarillas)
A4: Sueldo básico | B4: 2500
A5: Días laborados | B5: 30
A6: ¿Tiene hijos? | B6: No
A7: Sistema de pensiones | B7: ONP
A8: AFP | B8: AFP Ejemplo
A9: Horas extras al 25% | B9: 0
A10: Horas extras al 35% | B10: 0
A11: Adelantos | B11: 0
A12: Validación | B12: =IF(NOT(ISNUMBER(B4)),"El sueldo debe ser un número",IF(B4<=0,"El sueldo debe ser mayor que cero",IF(NOT(ISNUMBER(B5)),"Los días deben ser un número",IF(OR(B5<1,B5>30),"Los días deben estar entre 1 y 30",IF(OR(B9<0,B10<0),"Las horas extras no pueden ser negativas",IF(B11<0,"Los adelantos no pueden ser negativos","Datos válidos")))))) -> Datos válidos
A14: CÁLCULO
A15: Valor hora | B15: =B4/'Parámetros'!$B$9/'Parámetros'!$B$10 -> 10.416667 | C15: Sueldo básico ÷ 30 ÷ 8 (no se redondea, se redondea cada concepto)
A17: REMUNERACIONES
A18: Sueldo computable | B18: =ROUND(B4/'Parámetros'!$B$9*B5,2) -> 2500 | C18: Sueldo básico ÷ 30 × días laborados
A19: Asignación familiar | B19: =IF(B6="Sí",ROUND('Parámetros'!$B$4,2),0) -> 0 | C19: 10% de la RMV si tiene hijos (no se prorratea)
A20: Horas extras 25% | B20: =ROUND(B15*'Parámetros'!$B$7*B9,2) -> 0 | C20: Valor hora × 1.25 × horas
A21: Horas extras 35% | B21: =ROUND(B15*'Parámetros'!$B$8*B10,2) -> 0 | C21: Valor hora × 1.35 × horas
A22: Total remuneraciones | B22: =SUM(B18:B21) -> 2500 | C22: Suma de los conceptos anteriores
A24: RETENCIONES / DESCUENTOS
A25: ONP | B25: =IF(B7="ONP",ROUND(B22*'Parámetros'!$B$5,2),0) -> 325 | C25: 13% del total de remuneraciones (si es ONP)
A26: AFP fondo | B26: {=IF(B7="AFP",ROUND(B22*INDEX('Parámetros'!$B$14:$B$18,MATCH(B8,'Parámetros'!$A$14:$A$18,0)),2),0)} -> 0 | C26: Total remuneraciones × tasa de fondo (si es AFP)
A27: AFP comisión | B27: {=IF(B7="AFP",ROUND(B22*INDEX('Parámetros'!$C$14:$C$18,MATCH(B8,'Parámetros'!$A$14:$A$18,0)),2),0)} -> 0 | C27: Total remuneraciones × tasa de comisión (si es AFP)
A28: AFP seguro | B28: {=IF(B7="AFP",ROUND(B22*INDEX('Parámetros'!$D$14:$D$18,MATCH(B8,'Parámetros'!$A$14:$A$18,0)),2),0)} -> 0 | C28: Total remuneraciones × tasa de seguro (si es AFP)
A29: Adelantos | B29: =B11 -> 0 | C29: Se resta tal cual
A30: Total descuentos | B30: =SUM(B25:B29) -> 325 | C30: Pensión + adelantos
A32: APORTACIONES DEL EMPLEADOR
A33: EsSalud (9%) | B33: =ROUND(B22*'Parámetros'!$B$6,2) -> 225 | C33: Total remuneraciones × 9%. Lo paga el empleador
A35: NETO A PAGAR | B35: =IF(B12="Datos válidos",B22-B30,"Revisar datos") -> 2175 | C35: Total remuneraciones − total descuentos

Sheet Casos
A1: Casos de prueba (todo con fórmulas)
A3: Concepto | B3: Caso 1 | C3: Caso 2 | D3: Caso 3 | E3: Caso 4 | F3: Caso propio
A4: Sueldo básico | B4: 2500 | C4: 1800 | D4: 3000 | E4: 4200
A5: Días laborados | B5: 30 | C5: 27 | D5: 30 | E5: 24
A6: ¿Tiene hijos? | B6: No | C6: Sí | D6: Sí | E6: Sí
A7: Sistema de pensiones | B7: ONP | C7: ONP | D7: AFP | E7: AFP
A8: AFP | B8: - | C8: - | D8: AFP Ejemplo | E8: AFP Ejemplo
A9: Horas extras 25% | B9: 0 | C9: 0 | D9: 4 | E9: 2
A10: Horas extras 35% | B10: 0 | C10: 0 | D10: 4 | E10: 2
A11: Adelantos | B11: 0 | C11: 0 | D11: 200 | E11: 100
A12: Cálculo
A13: Valor hora | B13: =IF(B4="","",B4/'Parámetros'!$B$9/'Parámetros'!$B$10) -> 10.416667 | C13: =IF(C4="","",C4/'Parámetros'!$B$9/'Parámetros'!$B$10) -> 7.5 | D13: =IF(D4="","",D4/'Parámetros'!$B$9/'Parámetros'!$B$10) -> 12.5 | E13: =IF(E4="","",E4/'Parámetros'!$B$9/'Parámetros'!$B$10) -> 17.5 | F13: =IF(F4="","",F4/'Parámetros'!$B$9/'Parámetros'!$B$10)
A14: Sueldo computable | B14: =IF(B4="","",ROUND(B4/'Parámetros'!$B$9*B5,2)) -> 2500 | C14: =IF(C4="","",ROUND(C4/'Parámetros'!$B$9*C5,2)) -> 1620 | D14: =IF(D4="","",ROUND(D4/'Parámetros'!$B$9*D5,2)) -> 3000 | E14: =IF(E4="","",ROUND(E4/'Parámetros'!$B$9*E5,2)) -> 3360 | F14: =IF(F4="","",ROUND(F4/'Parámetros'!$B$9*F5,2))
A15: Asignación familiar | B15: =IF(B4="","",IF(B6="Sí",ROUND('Parámetros'!$B$4,2),0)) -> 0 | C15: =IF(C4="","",IF(C6="Sí",ROUND('Parámetros'!$B$4,2),0)) -> 123 | D15: =IF(D4="","",IF(D6="Sí",ROUND('Parámetros'!$B$4,2),0)) -> 123 | E15: =IF(E4="","",IF(E6="Sí",ROUND('Parámetros'!$B$4,2),0)) -> 123 | F15: =IF(F4="","",IF(F6="Sí",ROUND('Parámetros'!$B$4,2),0))
A16: Horas extras 25% | B16: =IF(B4="","",ROUND(B13*'Parámetros'!$B$7*B9,2)) -> 0 | C16: =IF(C4="","",ROUND(C13*'Parámetros'!$B$7*C9,2)) -> 0 | D16: =IF(D4="","",ROUND(D13*'Parámetros'!$B$7*D9,2)) -> 62.5 | E16: =IF(E4="","",ROUND(E13*'Parámetros'!$B$7*E9,2)) -> 43.75 | F16: =IF(F4="","",ROUND(F13*'Parámetros'!$B$7*F9,2))
A17: Horas extras 35% | B17: =IF(B4="","",ROUND(B13*'Parámetros'!$B$8*B10,2)) -> 0 | C17: =IF(C4="","",ROUND(C13*'Parámetros'!$B$8*C10,2)) -> 0 | D17: =IF(D4="","",ROUND(D13*'Parámetros'!$B$8*D10,2)) -> 67.5 | E17: =IF(E4="","",ROUND(E13*'Parámetros'!$B$8*E10,2)) -> 47.25 | F17: =IF(F4="","",ROUND(F13*'Parámetros'!$B$8*F10,2))
A18: Total remuneraciones | B18: =IF(B4="","",SUM(B14:B17)) -> 2500 | C18: =IF(C4="","",SUM(C14:C17)) -> 1743 | D18: =IF(D4="","",SUM(D14:D17)) -> 3253 | E18: =IF(E4="","",SUM(E14:E17)) -> 3574 | F18: =IF(F4="","",SUM(F14:F17))
A19: ONP | B19: =IF(B4="","",IF(B7="ONP",ROUND(B18*'Parámetros'!$B$5,2),0)) -> 325 | C19: =IF(C4="","",IF(C7="ONP",ROUND(C18*'Parámetros'!$B$5,2),0)) -> 226.59 | D19: =IF(D4="","",IF(D7="ONP",ROUND(D18*'Parámetros'!$B$5,2),0)) -> 0 | E19: =IF(E4="","",IF(E7="ONP",ROUND(E18*'Parámetros'!$B$5,2),0)) -> 0 | F19: =IF(F4="","",IF(F7="ONP",ROUND(F18*'Parámetros'!$B$5,2),0))
A20: AFP fondo | B20: {=IF(B4="","",IF(B7="AFP",ROUND(B18*INDEX('Parámetros'!$B$14:$B$18,MATCH(B8,'Parámetros'!$A$14:$A$18,0)),2),0))} -> 0 | C20: {=IF(C4="","",IF(C7="AFP",ROUND(C18*INDEX('Parámetros'!$B$14:$B$18,MATCH(C8,'Parámetros'!$A$14:$A$18,0)),2),0))} -> 0 | D20: {=IF(D4="","",IF(D7="AFP",ROUND(D18*INDEX('Parámetros'!$B$14:$B$18,MATCH(D8,'Parámetros'!$A$14:$A$18,0)),2),0))} -> 325.3 | E20: {=IF(E4="","",IF(E7="AFP",ROUND(E18*INDEX('Parámetros'!$B$14:$B$18,MATCH(E8,'Parámetros'!$A$14:$A$18,0)),2),0))} -> 357.4 | F20: {=IF(F4="","",IF(F7="AFP",ROUND(F18*INDEX('Parámetros'!$B$14:$B$18,MATCH(F8,'Parámetros'!$A$14:$A$18,0)),2),0))}
A21: AFP comisión | B21: {=IF(B4="","",IF(B7="AFP",ROUND(B18*INDEX('Parámetros'!$C$14:$C$18,MATCH(B8,'Parámetros'!$A$14:$A$18,0)),2),0))} -> 0 | C21: {=IF(C4="","",IF(C7="AFP",ROUND(C18*INDEX('Parámetros'!$C$14:$C$18,MATCH(C8,'Parámetros'!$A$14:$A$18,0)),2),0))} -> 0 | D21: {=IF(D4="","",IF(D7="AFP",ROUND(D18*INDEX('Parámetros'!$C$14:$C$18,MATCH(D8,'Parámetros'!$A$14:$A$18,0)),2),0))} -> 52.05 | E21: {=IF(E4="","",IF(E7="AFP",ROUND(E18*INDEX('Parámetros'!$C$14:$C$18,MATCH(E8,'Parámetros'!$A$14:$A$18,0)),2),0))} -> 57.18 | F21: {=IF(F4="","",IF(F7="AFP",ROUND(F18*INDEX('Parámetros'!$C$14:$C$18,MATCH(F8,'Parámetros'!$A$14:$A$18,0)),2),0))}
A22: AFP seguro | B22: {=IF(B4="","",IF(B7="AFP",ROUND(B18*INDEX('Parámetros'!$D$14:$D$18,MATCH(B8,'Parámetros'!$A$14:$A$18,0)),2),0))} -> 0 | C22: {=IF(C4="","",IF(C7="AFP",ROUND(C18*INDEX('Parámetros'!$D$14:$D$18,MATCH(C8,'Parámetros'!$A$14:$A$18,0)),2),0))} -> 0 | D22: {=IF(D4="","",IF(D7="AFP",ROUND(D18*INDEX('Parámetros'!$D$14:$D$18,MATCH(D8,'Parámetros'!$A$14:$A$18,0)),2),0))} -> 43.92 | E22: {=IF(E4="","",IF(E7="AFP",ROUND(E18*INDEX('Parámetros'!$D$14:$D$18,MATCH(E8,'Parámetros'!$A$14:$A$18,0)),2),0))} -> 48.25 | F22: {=IF(F4="","",IF(F7="AFP",ROUND(F18*INDEX('Parámetros'!$D$14:$D$18,MATCH(F8,'Parámetros'!$A$14:$A$18,0)),2),0))}
A23: Adelantos | B23: =IF(B4="","",B11) -> 0 | C23: =IF(C4="","",C11) -> 0 | D23: =IF(D4="","",D11) -> 200 | E23: =IF(E4="","",E11) -> 100 | F23: =IF(F4="","",F11)
A24: Total descuentos | B24: =IF(B4="","",SUM(B19:B23)) -> 325 | C24: =IF(C4="","",SUM(C19:C23)) -> 226.59 | D24: =IF(D4="","",SUM(D19:D23)) -> 621.27 | E24: =IF(E4="","",SUM(E19:E23)) -> 562.83 | F24: =IF(F4="","",SUM(F19:F23))
A25: NETO A PAGAR | B25: =IF(B4="","",B18-B24) -> 2175 | C25: =IF(C4="","",C18-C24) -> 1516.41 | D25: =IF(D4="","",D18-D24) -> 2631.73 | E25: =IF(E4="","",E18-E24) -> 3011.17 | F25: =IF(F4="","",F18-F24)
A26: EsSalud (empleador) | B26: =IF(B4="","",ROUND(B18*'Parámetros'!$B$6,2)) -> 225 | C26: =IF(C4="","",ROUND(C18*'Parámetros'!$B$6,2)) -> 156.87 | D26: =IF(D4="","",ROUND(D18*'Parámetros'!$B$6,2)) -> 292.77 | E26: =IF(E4="","",ROUND(E18*'Parámetros'!$B$6,2)) -> 321.66 | F26: =IF(F4="","",ROUND(F18*'Parámetros'!$B$6,2))
A28: Respuesta del documento
A29: Neto esperado | B29: 2175 | C29: 1516.41 | D29: 2631.73 | E29: Lo revisa el docente | F29: —
A30: EsSalud esperado | B30: 225 | C30: 156.87 | D30: 292.77
A31: ¿Coincide el neto? | B31: =IF(AND(ROUND(B25-B29,2)=0,ROUND(B26-B30,2)=0),"Sí","No") -> Sí | C31: =IF(AND(ROUND(C25-C29,2)=0,ROUND(C26-C30,2)=0),"Sí","No") -> Sí | D31: =IF(AND(ROUND(D25-D29,2)=0,ROUND(D26-D30,2)=0),"Sí","No") -> Sí | E31: — | F31: —
A33: El caso propio va con el sueldo de una oferta laboral real (guardar enlace y fecha de consulta).

Sheet Explicación
A1: Explicación de cada fórmula
A3: Concepto | B3: Qué es (en palabras) | C3: Cómo se calcula | D3: Ejemplo con números
A4: Sueldo computable | B4: Lo que le toca al trabajador por los días que sí trabajó. Se divide el sueldo entre 30 para sacar lo que gana por día y se multiplica por los días trabajados. | C4: Sueldo básico ÷ 30 × días laborados | D4: Caso 2: 1,800 ÷ 30 × 27 = 1,620.00
A5: Asignación familiar | B5: Un pago extra para quien tiene hijos. Siempre es el 10% de la RMV, aunque haya faltado días. | C5: 10% × RMV (solo si tiene hijos) | D5: 10% × 1,230 = 123.00
A6: Valor hora | B6: Cuánto vale una hora de trabajo normal. Sirve para pagar las horas extras. | C6: Sueldo básico ÷ 30 ÷ 8 | D6: Caso 3: 3,000 ÷ 30 ÷ 8 = 12.50
A7: Horas extras 25% | B7: Las primeras horas extra se pagan con un 25% más que una hora normal. | C7: Valor hora × 1.25 × horas | D7: Caso 3: 12.50 × 1.25 × 4 = 62.50
A8: Horas extras 35% | B8: Las horas extra que siguen se pagan con un 35% más. | C8: Valor hora × 1.35 × horas | D8: Caso 3: 12.50 × 1.35 × 4 = 67.50
A9: Total remuneraciones | B9: Todo lo que gana el trabajador en el mes antes de los descuentos. | C9: Suma de sueldo computable, asignación familiar y horas extras | D9: Caso 3: 3,000 + 123 + 62.50 + 67.50 = 3,253.00
A10: ONP | B10: Aporte para la pensión del Estado. Se descuenta el 13% del total de remuneraciones. | C10: Total remuneraciones × 13% | D10: Caso 2: 1,743 × 13% = 226.59
A11: AFP fondo | B11: Parte del descuento que va a la cuenta personal de pensión del trabajador. | C11: Total remuneraciones × tasa de fondo | D11: Caso 3: 3,253 × 10% = 325.30
A12: AFP comisión | B12: Lo que cobra la AFP por administrar el dinero. | C12: Total remuneraciones × tasa de comisión | D12: Caso 3: 3,253 × 1.60% = 52.048, se redondea a 52.05
A13: AFP seguro | B13: Seguro de invalidez y sobrevivencia que cobra la AFP. | C13: Total remuneraciones × tasa de seguro | D13: Caso 3: 3,253 × 1.35% = 43.9155, se redondea a 43.92
A14: Adelantos | B14: Plata que el trabajador ya recibió antes. Se resta completa. | C14: Monto ingresado | D14: Caso 3: 200.00
... A18: Redondeo | B18: Cada concepto se redondea a 2 decimales y recién después se suman. | C18: ROUND(valor; 2) | D18: 52.048 pasa a 52.05
A20: Respuestas a las preguntas de análisis
A21: Pregunta | B21: Respuesta | C21: Cuenta | D21: Resultado
A22: 1. ONP o AFP (datos del caso 3) | B22: Con AFP el neto es un poco mayor este mes (1.62 más). Pero no basta comparar porcentajes: en la ONP el aporte va a un fondo común del Estado y en la AFP una parte va a la cuenta personal del trabajador, y además las comisiones y el seguro cambian según la AFP. Conviene mirar también la pensión futura, no solo el neto de este mes. | C22: Neto ONP: 3,253.00 − (422.89 + 200.00) = 2,630.11. Neto AFP: 2,631.73 | D22: AFP deja 1.62 más
A23: 2. Costo real para la empresa (caso 3) | B23: La empresa gasta las remuneraciones más EsSalud. Al trabajador le llega como neto un poco menos de las tres cuartas partes. | C23: 3,253.00 + 292.77 = 3,545.77. Neto ÷ costo = 2,631.73 ÷ 3,545.77 | D23: Costo 3,545.77, llega 74.22%
A24: 3. Días laborados (caso 2 con 30 días) | B24: La diferencia en el neto es menor porque del sueldo extra se descuenta el 13% de ONP, y la asignación familiar no cambia con los días. | C24: Sueldo 1,800 + 123 = 1,923.00. ONP 1,923 × 13% = 249.99. Neto 1,673.01. Dif. neto: 1,673.01 − 1,516.41. Dif. bruto: 1,923 − 1,743 | D24: Neto +156.60 vs bruto +180.00
A25: 4. Horas extras (caso 3) | B25: Las horas extras son una parte pequeña del total. | C25: (62.50 + 67.50) ÷ 3,253.00 | D25: 4.00%
A26: 5. Con datos reales | B26: Pendiente: agregar la oferta laboral elegida (enlace y fecha), armar la boleta en la columna Caso propio de la hoja Casos y comparar con dos compañeros. | C26: — | D26: Pendiente
A28: Fuentes: ver la hoja Parámetros (dato, valor, fuente y fecha de consulta).
